setup.py
balthier_distributions/Binomialdistribution.py
balthier_distributions/Gaussiandistribution.py
balthier_distributions/Generaldistribution.py
balthier_distributions/__init__.py
balthier_distributions.egg-info/PKG-INFO
balthier_distributions.egg-info/SOURCES.txt
balthier_distributions.egg-info/dependency_links.txt
balthier_distributions.egg-info/not-zip-safe
balthier_distributions.egg-info/top_level.txt