Metadata-Version: 1.0
Name: balthier-distributions
Version: 0.25
Summary: Gaussian + Binomial distributions
Home-page: UNKNOWN
Author: UNKNOWN
Author-email: UNKNOWN
License: UNKNOWN
Platform: UNKNOWN
